[
    {
        "name": "Apollo-Client",
        "version": "V2"
    },
    {
        "enabled": false,
        "ingameOnly": true,
        "keybind": 7,
        "name": "Auto Clicker",
        "settings": [
            {
                "name": "Visable in Arraylist",
                "type": 0,
                "value": 1
            },
            {
                "name": "Right",
                "type": 0,
                "value": 0
            },
            {
                "name": "Left",
                "type": 0,
                "value": 1
            },
            {
                "name": "APS",
                "type": 1,
                "value": 10.0
            }
        ],
        "visible": true
    },
    {
        "enabled": false,
        "ingameOnly": true,
        "keybind": 82,
        "name": "Killaura",
        "settings": [
            {
                "name": "Visable in Arraylist",
                "type": 0,
                "value": 1
            },
            {
                "name": "Target Mode",
                "type": 2,
                "value": 0
            },
            {
                "name": "Rotations",
                "type": 2,
                "value": 0
            },
            {
                "name": "Side",
                "type": 2,
                "value": 0
            },
            {
                "name": "Swing",
                "type": 2,
                "value": 0
            },
            {
                "name": "AutoSlot",
                "type": 2,
                "value": 1
            },
            {
                "name": "Bypass",
                "type": 2,
                "value": 0
            },
            {
                "name": "Range",
                "type": 1,
                "value": 4.532432556152344
            },
            {
                "name": "APS",
                "type": 1,
                "value": 8.270270347595215
            },
            {
                "name": "Strafe",
                "type": 0,
                "value": 0
            },
            {
                "name": "Timed swing",
                "type": 0,
                "value": 1
            },
            {
                "name": "Auto Ember Sword",
                "type": 0,
                "value": 0
            },
            {
                "name": "Nemo",
                "type": 0,
                "value": 0
            },
            {
                "name": "Silent",
                "type": 0,
                "value": 0
            },
            {
                "name": "Projectiles",
                "type": 0,
                "value": 0
            },
            {
                "name": "Speed",
                "type": 1,
                "value": 10.0
            }
        ],
        "visible": true
    },
    {
        "enabled": true,
        "ingameOnly": true,
        "keybind": 7,
        "name": "Teams",
        "settings": [
            {
                "name": "Visable in Arraylist",
                "type": 0,
                "value": 0
            }
        ],
        "visible": false
    },
    {
        "enabled": false,
        "ingameOnly": true,
        "keybind": 7,
        "name": "Anti Regen",
        "settings": [
            {
                "name": "Visable in Arraylist",
                "type": 0,
                "value": 1
            },
            {
                "name": "Range",
                "type": 1,
                "value": 1.5
            },
            {
                "name": "Blocks",
                "type": 1,
                "value": 1.0
            }
        ],
        "visible": true
    },
    {
        "enabled": false,
        "ingameOnly": true,
        "keybind": 7,
        "name": "AutoBoombox",
        "settings": [
            {
                "name": "Visable in Arraylist",
                "type": 0,
                "value": 1
            },
            {
                "name": "Range",
                "type": 1,
                "value": 1.5
            }
        ],
        "visible": true
    },
    {
        "enabled": false,
        "ingameOnly": true,
        "keybind": 7,
        "name": "AutoLootbox",
        "settings": [
            {
                "name": "Visable in Arraylist",
                "type": 0,
                "value": 1
            },
            {
                "name": "Distance",
                "type": 1,
                "value": 6.0
            }
        ],
        "visible": true
    },
    {
        "enabled": true,
        "ingameOnly": true,
        "keybind": 7,
        "name": "AutoQueue",
        "settings": [
            {
                "name": "Visable in Arraylist",
                "type": 0,
                "value": 0
            },
            {
                "name": "Queued On Game End",
                "type": 0,
                "value": 1
            },
            {
                "name": "Queued On Death",
                "type": 0,
                "value": 1
            }
        ],
        "visible": false
    },
    {
        "enabled": true,
        "ingameOnly": true,
        "keybind": 7,
        "name": "AutoTool",
        "settings": [
            {
                "name": "Visable in Arraylist",
                "type": 0,
                "value": 0
            },
            {
                "name": "Spoof",
                "type": 0,
                "value": 0
            }
        ],
        "visible": false
    },
    {
        "enabled": false,
        "ingameOnly": true,
        "keybind": 7,
        "name": "Desync",
        "settings": [
            {
                "name": "Visable in Arraylist",
                "type": 0,
                "value": 1
            },
            {
                "name": "Desync Value",
                "type": 1,
                "value": 500.0
            }
        ],
        "visible": true
    },
    {
        "enabled": false,
        "ingameOnly": true,
        "keybind": 7,
        "name": "Disabler",
        "settings": [
            {
                "name": "Visable in Arraylist",
                "type": 0,
                "value": 1
            },
            {
                "name": "Mode",
                "type": 2,
                "value": 0
            },
            {
                "name": "Timer Value",
                "type": 1,
                "value": 0.4000000059604645
            },
            {
                "name": "Send Packets",
                "type": 0,
                "value": 0
            },
            {
                "name": "Speed Strafe",
                "type": 0,
                "value": 0
            },
            {
                "name": "Only Fly",
                "type": 0,
                "value": 1
            },
            {
                "name": "Only PlayerAuth",
                "type": 0,
                "value": 0
            },
            {
                "name": "Debug",
                "type": 0,
                "value": 0
            },
            {
                "name": "Display Mode",
                "type": 0,
                "value": 1
            }
        ],
        "visible": true
    },
    {
        "enabled": false,
        "ingameOnly": true,
        "keybind": 7,
        "name": "FastBreak",
        "settings": [
            {
                "name": "Visable in Arraylist",
                "type": 0,
                "value": 1
            },
            {
                "name": "Speed",
                "type": 1,
                "value": 10.0
            }
        ],
        "visible": true
    },
    {
        "enabled": false,
        "ingameOnly": true,
        "keybind": 7,
        "name": "Fat ngga",
        "settings": [
            {
                "name": "Visable in Arraylist",
                "type": 0,
                "value": 1
            },
            {
                "name": "Mode",
                "type": 2,
                "value": 0
            },
            {
                "name": "Radius",
                "type": 1,
                "value": 3.0
            },
            {
                "name": "Ore Keeper",
                "type": 0,
                "value": 0
            }
        ],
        "visible": true
    },
    {
        "enabled": false,
        "ingameOnly": true,
        "keybind": 7,
        "name": "Freecam",
        "settings": [
            {
                "name": "Visable in Arraylist",
                "type": 0,
                "value": 1
            }
        ],
        "visible": true
    },
    {
        "enabled": false,
        "ingameOnly": true,
        "keybind": 7,
        "name": "Goofy",
        "settings": [
            {
                "name": "Visable in Arraylist",
                "type": 0,
                "value": 1
            },
            {
                "name": "Range",
                "type": 1,
                "value": 1.5
            },
            {
                "name": "Prediction",
                "type": 1,
                "value": 1.0
            },
            {
                "name": "TickGap",
                "type": 1,
                "value": 0.0
            },
            {
                "name": "Advanced",
                "type": 0,
                "value": 0
            },
            {
                "name": "Teams",
                "type": 0,
                "value": 1
            }
        ],
        "visible": true
    },
    {
        "enabled": false,
        "ingameOnly": true,
        "keybind": 7,
        "name": "IRC",
        "settings": [
            {
                "name": "Visable in Arraylist",
                "type": 0,
                "value": 1
            }
        ],
        "visible": true
    },
    {
        "enabled": false,
        "ingameOnly": true,
        "keybind": 7,
        "name": "KickDecryptor",
        "settings": [
            {
                "name": "Visable in Arraylist",
                "type": 0,
                "value": 1
            }
        ],
        "visible": true
    },
    {
        "enabled": false,
        "ingameOnly": true,
        "keybind": 88,
        "name": "Net Skip",
        "settings": [
            {
                "name": "Visable in Arraylist",
                "type": 0,
                "value": 1
            },
            {
                "name": "Mode",
                "type": 2,
                "value": 0
            },
            {
                "name": "Ms",
                "type": 1,
                "value": 500.0
            }
        ],
        "visible": true
    },
    {
        "enabled": false,
        "ingameOnly": true,
        "keybind": 7,
        "name": "NoPacket",
        "settings": [
            {
                "name": "Visable in Arraylist",
                "type": 0,
                "value": 1
            }
        ],
        "visible": true
    },
    {
        "enabled": false,
        "ingameOnly": true,
        "keybind": 7,
        "name": "OreMiner",
        "settings": [
            {
                "name": "Visable in Arraylist",
                "type": 0,
                "value": 1
            },
            {
                "name": "Mode",
                "type": 2,
                "value": 0
            },
            {
                "name": "Priority",
                "type": 2,
                "value": 0
            },
            {
                "name": "Range",
                "type": 1,
                "value": 5.0
            },
            {
                "name": "Time MS",
                "type": 1,
                "value": 800.0
            }
        ],
        "visible": true
    },
    {
        "enabled": false,
        "ingameOnly": true,
        "keybind": 7,
        "name": "PacketMine",
        "settings": [
            {
                "name": "Visable in Arraylist",
                "type": 0,
                "value": 1
            }
        ],
        "visible": true
    },
    {
        "enabled": false,
        "ingameOnly": true,
        "keybind": 7,
        "name": "Ping Holder",
        "settings": [
            {
                "name": "Visable in Arraylist",
                "type": 0,
                "value": 1
            },
            {
                "name": "Ping",
                "type": 1,
                "value": 70.0
            },
            {
                "name": "Randomize",
                "type": 0,
                "value": 1
            },
            {
                "name": "Low Ping",
                "type": 1,
                "value": 30.0
            },
            {
                "name": "High Ping",
                "type": 1,
                "value": 40.0
            }
        ],
        "visible": true
    },
    {
        "enabled": false,
        "ingameOnly": true,
        "keybind": 86,
        "name": "Regen",
        "settings": [
            {
                "name": "Visable in Arraylist",
                "type": 0,
                "value": 1
            },
            {
                "name": "Mode",
                "type": 2,
                "value": 0
            },
            {
                "name": "Uncover Mode",
                "type": 2,
                "value": 1
            },
            {
                "name": "Side",
                "type": 2,
                "value": 0
            },
            {
                "name": "Range",
                "type": 1,
                "value": 7.991892337799072
            },
            {
                "name": "Destroy Speed",
                "type": 1,
                "value": 77.02703094482422
            },
            {
                "name": "Uncover",
                "type": 0,
                "value": 1
            },
            {
                "name": "Queue",
                "type": 0,
                "value": 0
            },
            {
                "name": "Debug",
                "type": 0,
                "value": 0
            },
            {
                "name": "Steal",
                "type": 0,
                "value": 0
            },
            {
                "name": "Always Steal",
                "type": 0,
                "value": 0
            },
            {
                "name": "Anti Steal",
                "type": 0,
                "value": 0
            },
            {
                "name": "Anti Cover",
                "type": 0,
                "value": 0
            },
            {
                "name": "Compensation",
                "type": 1,
                "value": 100.0
            },
            {
                "name": "Durability Exploit",
                "type": 0,
                "value": 0
            },
            {
                "name": "Hotbar Only",
                "type": 0,
                "value": 1
            },
            {
                "name": "Visual",
                "type": 2,
                "value": 2
            }
        ],
        "visible": true
    },
    {
        "enabled": false,
        "ingameOnly": true,
        "keybind": 7,
        "name": "RegenOld",
        "settings": [
            {
                "name": "Visable in Arraylist",
                "type": 0,
                "value": 1
            },
            {
                "name": "Mode",
                "type": 2,
                "value": 0
            },
            {
                "name": "Uncover Mode",
                "type": 2,
                "value": 0
            },
            {
                "name": "Side",
                "type": 2,
                "value": 0
            },
            {
                "name": "Range",
                "type": 1,
                "value": 5.0
            },
            {
                "name": "Time MS",
                "type": 1,
                "value": 550.0
            },
            {
                "name": "Other MS",
                "type": 1,
                "value": 550.0
            },
            {
                "name": "Destroy Speed",
                "type": 1,
                "value": 1.0
            },
            {
                "name": "Other Destroy Speed",
                "type": 1,
                "value": 1.0
            },
            {
                "name": "Insta Break Steal",
                "type": 0,
                "value": 0
            },
            {
                "name": "Steal",
                "type": 0,
                "value": 0
            },
            {
                "name": "Always Steal",
                "type": 0,
                "value": 0
            },
            {
                "name": "Steal Mode",
                "type": 2,
                "value": 0
            },
            {
                "name": "Steal Speed",
                "type": 1,
                "value": 0.75
            },
            {
                "name": "Steal MS",
                "type": 1,
                "value": 490.0
            },
            {
                "name": "Legit Mine",
                "type": 0,
                "value": 1
            },
            {
                "name": "Legit Multiplier",
                "type": 0,
                "value": 0
            },
            {
                "name": "Low Multiplier",
                "type": 1,
                "value": 0.75
            },
            {
                "name": "Exposed Only",
                "type": 0,
                "value": 1
            },
            {
                "name": "Queue",
                "type": 0,
                "value": 0
            },
            {
                "name": "Debug",
                "type": 0,
                "value": 0
            },
            {
                "name": "Durability Exploit",
                "type": 0,
                "value": 0
            },
            {
                "name": "Render",
                "type": 0,
                "value": 1
            }
        ],
        "visible": true
    },
    {
        "enabled": false,
        "ingameOnly": true,
        "keybind": 67,
        "name": "Scaffold",
        "settings": [
            {
                "name": "Visable in Arraylist",
                "type": 0,
                "value": 1
            },
            {
                "name": "Rotations",
                "type": 2,
                "value": 0
            },
            {
                "name": "Side",
                "type": 2,
                "value": 0
            },
            {
                "name": "Switch",
                "type": 2,
                "value": 0
            },
            {
                "name": "Swing",
                "type": 2,
                "value": 0
            },
            {
                "name": "TowerMode",
                "type": 2,
                "value": 0
            },
            {
                "name": "Placement",
                "type": 2,
                "value": 1
            },
            {
                "name": "Counter",
                "type": 2,
                "value": 1
            },
            {
                "name": "Inventory Slot",
                "type": 0,
                "value": 1
            },
            {
                "name": "Flareon V2",
                "type": 0,
                "value": 0
            },
            {
                "name": "Aura Bypass",
                "type": 0,
                "value": 0
            },
            {
                "name": "Keep Y",
                "type": 0,
                "value": 1
            },
            {
                "name": "PlacesPerTick",
                "type": 1,
                "value": 0.800000011920929
            },
            {
                "name": "Distance",
                "type": 1,
                "value": 5.0
            },
            {
                "name": "Extend",
                "type": 1,
                "value": 3.0
            }
        ],
        "visible": true
    },
    {
        "enabled": false,
        "ingameOnly": true,
        "keybind": 7,
        "name": "Surround",
        "settings": [
            {
                "name": "Visable in Arraylist",
                "type": 0,
                "value": 1
            },
            {
                "name": "PlaceMode",
                "type": 2,
                "value": 0
            },
            {
                "name": "Range",
                "type": 1,
                "value": 1.5
            },
            {
                "name": "Prediction",
                "type": 1,
                "value": 1.0
            },
            {
                "name": "Place Limitter",
                "type": 1,
                "value": 1.0
            },
            {
                "name": "Place Distance",
                "type": 1,
                "value": 1.0
            },
            {
                "name": "Smart Place",
                "type": 0,
                "value": 0
            }
        ],
        "visible": true
    },
    {
        "enabled": false,
        "ingameOnly": true,
        "keybind": 7,
        "name": "TestModule",
        "settings": [
            {
                "name": "Visable in Arraylist",
                "type": 0,
                "value": 1
            },
            {
                "name": "Interact",
                "type": 2,
                "value": 0
            },
            {
                "name": "Test",
                "type": 0,
                "value": 1
            },
            {
                "name": "Test",
                "type": 1,
                "value": 1.5
            },
            {
                "name": "Boost",
                "type": 1,
                "value": 0.699999988079071
            },
            {
                "name": "Timer",
                "type": 1,
                "value": 7.300000190734863
            },
            {
                "name": "Glider",
                "type": 1,
                "value": -0.029999999329447746
            }
        ],
        "visible": true
    },
    {
        "enabled": false,
        "ingameOnly": true,
        "keybind": 70,
        "name": "Timer",
        "settings": [
            {
                "name": "Visable in Arraylist",
                "type": 0,
                "value": 0
            },
            {
                "name": "Timer",
                "type": 1,
                "value": 21.567567825317383
            }
        ],
        "visible": false
    },
    {
        "enabled": false,
        "ingameOnly": true,
        "keybind": 7,
        "name": "Airjump",
        "settings": [
            {
                "name": "Visable in Arraylist",
                "type": 0,
                "value": 1
            }
        ],
        "visible": true
    },
    {
        "enabled": false,
        "ingameOnly": true,
        "keybind": 7,
        "name": "AntiVoid",
        "settings": [
            {
                "name": "Visable in Arraylist",
                "type": 0,
                "value": 1
            },
            {
                "name": "Distance",
                "type": 1,
                "value": 1.0
            }
        ],
        "visible": true
    },
    {
        "enabled": true,
        "ingameOnly": true,
        "keybind": 7,
        "name": "FastStop",
        "settings": [
            {
                "name": "Visable in Arraylist",
                "type": 0,
                "value": 0
            },
            {
                "name": "Speed",
                "type": 1,
                "value": 6.0
            }
        ],
        "visible": false
    },
    {
        "enabled": false,
        "ingameOnly": true,
        "keybind": 88,
        "name": "Fly",
        "settings": [
            {
                "name": "Visable in Arraylist",
                "type": 0,
                "value": 1
            },
            {
                "name": "Mode",
                "type": 2,
                "value": 1
            },
            {
                "name": "Speed",
                "type": 1,
                "value": 2.0
            },
            {
                "name": "Glide",
                "type": 1,
                "value": -1.0
            },
            {
                "name": "Friction",
                "type": 1,
                "value": 0.0
            },
            {
                "name": "Blink",
                "type": 0,
                "value": 0
            },
            {
                "name": "Timer Value",
                "type": 1,
                "value": 20.829729080200195
            },
            {
                "name": "Boost Value",
                "type": 1,
                "value": -0.20000000298023224
            }
        ],
        "visible": true
    },
    {
        "enabled": false,
        "ingameOnly": true,
        "keybind": 7,
        "name": "Hive Fly",
        "settings": [
            {
                "name": "Visable in Arraylist",
                "type": 0,
                "value": 1
            },
            {
                "name": "SpeedMode",
                "type": 2,
                "value": 0
            },
            {
                "name": "TimerMode",
                "type": 2,
                "value": 0
            },
            {
                "name": "Speed",
                "type": 1,
                "value": 40.0
            },
            {
                "name": "SpeedMin",
                "type": 1,
                "value": 40.0
            },
            {
                "name": "SpeedMax",
                "type": 1,
                "value": 50.0
            },
            {
                "name": "SpeedMultiplier",
                "type": 1,
                "value": 1.0
            },
            {
                "name": "Timer",
                "type": 1,
                "value": 0.4000000059604645
            },
            {
                "name": "TimerMin",
                "type": 1,
                "value": 1.0
            },
            {
                "name": "TimerMax",
                "type": 1,
                "value": 3.0
            },
            {
                "name": "TimerMultiplier",
                "type": 1,
                "value": 1.0
            },
            {
                "name": "Glide",
                "type": 1,
                "value": 0.0
            },
            {
                "name": "NetSkipMs",
                "type": 1,
                "value": 0.0
            },
            {
                "name": "NetSkip",
                "type": 0,
                "value": 0
            },
            {
                "name": "Debug",
                "type": 0,
                "value": 0
            }
        ],
        "visible": true
    },
    {
        "enabled": false,
        "ingameOnly": true,
        "keybind": 7,
        "name": "LongJump",
        "settings": [
            {
                "name": "Visable in Arraylist",
                "type": 0,
                "value": 1
            },
            {
                "name": "Mode",
                "type": 2,
                "value": 0
            },
            {
                "name": "Fall",
                "type": 2,
                "value": 0
            },
            {
                "name": "Fricton",
                "type": 2,
                "value": 0
            },
            {
                "name": "Speed",
                "type": 1,
                "value": 3.0
            },
            {
                "name": "Height",
                "type": 1,
                "value": 0.0
            },
            {
                "name": "Timer",
                "type": 1,
                "value": 20.0
            },
            {
                "name": "FallSpeed (Multiplier)",
                "type": 1,
                "value": 1.0
            },
            {
                "name": "FallSpeed (Add)",
                "type": 1,
                "value": 0.0
            },
            {
                "name": "Friction (Multiplier)",
                "type": 1,
                "value": 0.9800000190734863
            },
            {
                "name": "Friction (Add)",
                "type": 1,
                "value": 0.0
            },
            {
                "name": "Boost Timing",
                "type": 1,
                "value": 1.0
            },
            {
                "name": "Debug",
                "type": 0,
                "value": 0
            }
        ],
        "visible": true
    },
    {
        "enabled": false,
        "ingameOnly": true,
        "keybind": 7,
        "name": "NoSlowdown",
        "settings": [
            {
                "name": "Visable in Arraylist",
                "type": 0,
                "value": 1
            }
        ],
        "visible": true
    },
    {
        "enabled": false,
        "ingameOnly": true,
        "keybind": 70,
        "name": "Speed",
        "settings": [
            {
                "name": "Visable in Arraylist",
                "type": 0,
                "value": 1
            },
            {
                "name": "Mode",
                "type": 2,
                "value": 1
            },
            {
                "name": "Speed",
                "type": 1,
                "value": 3.797297239303589
            },
            {
                "name": "SwiftSpeed",
                "type": 1,
                "value": 1.0
            },
            {
                "name": "Height",
                "type": 1,
                "value": 2.7054054737091064
            },
            {
                "name": "Friction",
                "type": 1,
                "value": 10.0
            },
            {
                "name": "AutoSwiftness",
                "type": 0,
                "value": 1
            },
            {
                "name": "Timer",
                "type": 1,
                "value": 20.594594955444336
            },
            {
                "name": "Fast Fall",
                "type": 0,
                "value": 0
            },
            {
                "name": "Fall Speed",
                "type": 1,
                "value": 2.0
            },
            {
                "name": "DamageBoost",
                "type": 0,
                "value": 0
            },
            {
                "name": "DamageBoostSpeed",
                "type": 1,
                "value": 0.0
            },
            {
                "name": "Down Value",
                "type": 1,
                "value": 0.0
            },
            {
                "name": "Up Timer",
                "type": 1,
                "value": 20.124324798583984
            },
            {
                "name": "Down Timer",
                "type": 1,
                "value": 20.308107376098633
            },
            {
                "name": "Down Timing (Min)",
                "type": 1,
                "value": 1.0
            },
            {
                "name": "Down Timing (Max)",
                "type": 1,
                "value": 1.0
            },
            {
                "name": "Boost Timing (Min)",
                "type": 1,
                "value": 1.0
            },
            {
                "name": "Boost Timing (Max)",
                "type": 1,
                "value": 1.0
            },
            {
                "name": "Boost",
                "type": 0,
                "value": 0
            }
        ],
        "visible": true
    },
    {
        "enabled": true,
        "ingameOnly": true,
        "keybind": 7,
        "name": "Sprint",
        "settings": [
            {
                "name": "Visable in Arraylist",
                "type": 0,
                "value": 0
            },
            {
                "name": "Mode",
                "type": 2,
                "value": 0
            }
        ],
        "visible": false
    },
    {
        "enabled": false,
        "ingameOnly": true,
        "keybind": 7,
        "name": "Step",
        "settings": [
            {
                "name": "Visable in Arraylist",
                "type": 0,
                "value": 1
            },
            {
                "name": "Mode",
                "type": 2,
                "value": 0
            },
            {
                "name": "Height",
                "type": 1,
                "value": 1.2999999523162842
            }
        ],
        "visible": true
    },
    {
        "enabled": true,
        "ingameOnly": true,
        "keybind": 7,
        "name": "Velocity",
        "settings": [
            {
                "name": "Visable in Arraylist",
                "type": 0,
                "value": 0
            }
        ],
        "visible": false
    },
    {
        "enabled": false,
        "ingameOnly": true,
        "keybind": 7,
        "name": "AntiImmobile",
        "settings": [
            {
                "name": "Visable in Arraylist",
                "type": 0,
                "value": 1
            }
        ],
        "visible": true
    },
    {
        "enabled": false,
        "ingameOnly": true,
        "keybind": 7,
        "name": "AutoSpellbook",
        "settings": [
            {
                "name": "Visable in Arraylist",
                "type": 0,
                "value": 1
            }
        ],
        "visible": true
    },
    {
        "enabled": true,
        "ingameOnly": true,
        "keybind": 7,
        "name": "ChestStealer",
        "settings": [
            {
                "name": "Visable in Arraylist",
                "type": 0,
                "value": 0
            },
            {
                "name": "SPS",
                "type": 1,
                "value": 20.0
            }
        ],
        "visible": false
    },
    {
        "enabled": false,
        "ingameOnly": true,
        "keybind": 7,
        "name": "Derp",
        "settings": [
            {
                "name": "Visable in Arraylist",
                "type": 0,
                "value": 1
            },
            {
                "name": "Side",
                "type": 2,
                "value": 0
            },
            {
                "name": "Pitch",
                "type": 0,
                "value": 0
            },
            {
                "name": "HeadYaw",
                "type": 0,
                "value": 0
            }
        ],
        "visible": true
    },
    {
        "enabled": false,
        "ingameOnly": true,
        "keybind": 7,
        "name": "ExperiencePoints",
        "settings": [
            {
                "name": "Visable in Arraylist",
                "type": 0,
                "value": 1
            },
            {
                "name": "Amount",
                "type": 1,
                "value": 300.0
            }
        ],
        "visible": true
    },
    {
        "enabled": true,
        "ingameOnly": true,
        "keybind": 7,
        "name": "InventoryManager",
        "settings": [
            {
                "name": "Visable in Arraylist",
                "type": 0,
                "value": 0
            },
            {
                "name": "Mode",
                "type": 2,
                "value": 0
            },
            {
                "name": "Drop",
                "type": 2,
                "value": 2
            },
            {
                "name": "Tools",
                "type": 2,
                "value": 1
            },
            {
                "name": "AutoArmor",
                "type": 0,
                "value": 1
            },
            {
                "name": "SortSword",
                "type": 0,
                "value": 1
            },
            {
                "name": "KeepBoomBox",
                "type": 0,
                "value": 1
            },
            {
                "name": "KeepEmberSword",
                "type": 0,
                "value": 1
            },
            {
                "name": "KeepSpells",
                "type": 0,
                "value": 1
            },
            {
                "name": "Delay",
                "type": 1,
                "value": 0.0
            }
        ],
        "visible": false
    },
    {
        "enabled": true,
        "ingameOnly": true,
        "keybind": 7,
        "name": "InvMove",
        "settings": [
            {
                "name": "Visable in Arraylist",
                "type": 0,
                "value": 0
            },
            {
                "name": "Speed",
                "type": 1,
                "value": 0.4320000112056732
            },
            {
                "name": "Height",
                "type": 1,
                "value": 0.41999998688697815
            }
        ],
        "visible": false
    },
    {
        "enabled": false,
        "ingameOnly": true,
        "keybind": 7,
        "name": "Killsults",
        "settings": [
            {
                "name": "Visable in Arraylist",
                "type": 0,
                "value": 1
            },
            {
                "name": "Mode",
                "type": 2,
                "value": 0
            },
            {
                "name": "Notification",
                "type": 0,
                "value": 1
            },
            {
                "name": "Sound",
                "type": 0,
                "value": 1
            },
            {
                "name": "Mention Player",
                "type": 0,
                "value": 1
            }
        ],
        "visible": true
    },
    {
        "enabled": false,
        "ingameOnly": true,
        "keybind": 7,
        "name": "MidClickPearl",
        "settings": [
            {
                "name": "Visable in Arraylist",
                "type": 0,
                "value": 1
            }
        ],
        "visible": true
    },
    {
        "enabled": false,
        "ingameOnly": true,
        "keybind": 7,
        "name": "No Jump Delay",
        "settings": [
            {
                "name": "Visable in Arraylist",
                "type": 0,
                "value": 1
            }
        ],
        "visible": true
    },
    {
        "enabled": false,
        "ingameOnly": true,
        "keybind": 7,
        "name": "NoRotate",
        "settings": [
            {
                "name": "Visable in Arraylist",
                "type": 0,
                "value": 1
            }
        ],
        "visible": true
    },
    {
        "enabled": false,
        "ingameOnly": true,
        "keybind": 7,
        "name": "NoSwing",
        "settings": [
            {
                "name": "Visable in Arraylist",
                "type": 0,
                "value": 1
            }
        ],
        "visible": true
    },
    {
        "enabled": false,
        "ingameOnly": true,
        "keybind": 7,
        "name": "Phase",
        "settings": [
            {
                "name": "Visable in Arraylist",
                "type": 0,
                "value": 1
            },
            {
                "name": "Mode",
                "type": 2,
                "value": 0
            },
            {
                "name": "Speed",
                "type": 1,
                "value": 0.5
            }
        ],
        "visible": true
    },
    {
        "enabled": false,
        "ingameOnly": true,
        "keybind": 7,
        "name": "Ambience",
        "settings": [
            {
                "name": "Visable in Arraylist",
                "type": 0,
                "value": 1
            },
            {
                "name": "Rain",
                "type": 0,
                "value": 0
            },
            {
                "name": "Time",
                "type": 0,
                "value": 1
            },
            {
                "name": "RainLevel",
                "type": 1,
                "value": 0.4000000059604645
            },
            {
                "name": "Time",
                "type": 1,
                "value": 15000.0
            }
        ],
        "visible": true
    },
    {
        "enabled": false,
        "ingameOnly": true,
        "keybind": 7,
        "name": "Animations",
        "settings": [
            {
                "name": "Visable in Arraylist",
                "type": 0,
                "value": 1
            },
            {
                "name": "Swing",
                "type": 2,
                "value": 0
            },
            {
                "name": "Swing Speed",
                "type": 1,
                "value": 13.0
            },
            {
                "name": "CustomSwingAngle",
                "type": 0,
                "value": 0
            },
            {
                "name": "Swing Angle",
                "type": 1,
                "value": 12.0
            }
        ],
        "visible": true
    },
    {
        "enabled": false,
        "ingameOnly": true,
        "keybind": 7,
        "name": "AntiInvis",
        "settings": [
            {
                "name": "Visable in Arraylist",
                "type": 0,
                "value": 1
            }
        ],
        "visible": true
    },
    {
        "enabled": true,
        "ingameOnly": true,
        "keybind": 7,
        "name": "Arraylist",
        "settings": [
            {
                "name": "Visable in Arraylist",
                "type": 0,
                "value": 1
            },
            {
                "name": "Style",
                "type": 2,
                "value": 0
            },
            {
                "name": "Animation",
                "type": 2,
                "value": 0
            },
            {
                "name": "Blur",
                "type": 0,
                "value": 0
            },
            {
                "name": "Blur Strength",
                "type": 1,
                "value": 9.0
            },
            {
                "name": "Size",
                "type": 1,
                "value": 10.5
            },
            {
                "name": "Padding",
                "type": 1,
                "value": 10.5
            },
            {
                "name": "Text Shadow",
                "type": 0,
                "value": 0
            },
            {
                "name": "Shadow",
                "type": 0,
                "value": 0
            },
            {
                "name": "Fill Shadow",
                "type": 0,
                "value": 0
            },
            {
                "name": "Shadow strenght",
                "type": 1,
                "value": 0.0
            },
            {
                "name": "Shadow opacity",
                "type": 1,
                "value": 0.0
            },
            {
                "name": "Bar opacity",
                "type": 1,
                "value": 40.81081008911133
            },
            {
                "name": "Opacity",
                "type": 1,
                "value": 50.0
            },
            {
                "name": "Rounding",
                "type": 1,
                "value": 0.0
            },
            {
                "name": "Font",
                "type": 2,
                "value": 2
            }
        ],
        "visible": true
    },
    {
        "enabled": false,
        "ingameOnly": true,
        "keybind": 7,
        "name": "Block ESP",
        "settings": [
            {
                "name": "Visable in Arraylist",
                "type": 0,
                "value": 1
            },
            {
                "name": "Style",
                "type": 2,
                "value": 0
            },
            {
                "name": "Range",
                "type": 1,
                "value": 5.0
            },
            {
                "name": "Iron",
                "type": 0,
                "value": 0
            },
            {
                "name": "Gold",
                "type": 0,
                "value": 0
            },
            {
                "name": "lapis",
                "type": 0,
                "value": 0
            },
            {
                "name": "Redstone",
                "type": 0,
                "value": 0
            },
            {
                "name": "Diamond",
                "type": 0,
                "value": 0
            },
            {
                "name": "Emerald",
                "type": 0,
                "value": 0
            },
            {
                "name": "Opacity",
                "type": 1,
                "value": 50.0
            },
            {
                "name": "Line",
                "type": 1,
                "value": 1.0
            }
        ],
        "visible": true
    },
    {
        "enabled": false,
        "ingameOnly": false,
        "keybind": 45,
        "name": "ClickGUI",
        "settings": [
            {
                "name": "Visable in Arraylist",
                "type": 0,
                "value": 1
            },
            {
                "name": "Style",
                "type": 2,
                "value": 1
            },
            {
                "name": "Animation",
                "type": 2,
                "value": 0
            },
            {
                "name": "Blur",
                "type": 0,
                "value": 1
            },
            {
                "name": "EaseSpeed",
                "type": 1,
                "value": 10.5
            }
        ],
        "visible": true
    },
    {
        "enabled": true,
        "ingameOnly": true,
        "keybind": 7,
        "name": "Destroy Progress",
        "settings": [
            {
                "name": "Visable in Arraylist",
                "type": 0,
                "value": 0
            },
            {
                "name": "LineWidth",
                "type": 1,
                "value": 1.0
            },
            {
                "name": "Opacity",
                "type": 1,
                "value": 75.0
            }
        ],
        "visible": false
    },
    {
        "enabled": true,
        "ingameOnly": true,
        "keybind": 7,
        "name": "ESP",
        "settings": [
            {
                "name": "Visable in Arraylist",
                "type": 0,
                "value": 0
            },
            {
                "name": "Style",
                "type": 2,
                "value": 0
            },
            {
                "name": "Range",
                "type": 1,
                "value": 40.0
            },
            {
                "name": "Thickness",
                "type": 1,
                "value": 2.0
            },
            {
                "name": "Alpha",
                "type": 1,
                "value": 1.0
            },
            {
                "name": "Rounding",
                "type": 1,
                "value": 0.0
            },
            {
                "name": "Self",
                "type": 0,
                "value": 0
            },
            {
                "name": "Ease",
                "type": 0,
                "value": 0
            }
        ],
        "visible": false
    },
    {
        "enabled": false,
        "ingameOnly": true,
        "keybind": 7,
        "name": "Fullbright",
        "settings": [
            {
                "name": "Visable in Arraylist",
                "type": 0,
                "value": 1
            }
        ],
        "visible": true
    },
    {
        "enabled": false,
        "ingameOnly": true,
        "keybind": 7,
        "name": "Glint",
        "settings": [
            {
                "name": "Visable in Arraylist",
                "type": 0,
                "value": 1
            }
        ],
        "visible": true
    },
    {
        "enabled": false,
        "ingameOnly": true,
        "keybind": 7,
        "name": "Hurtcolor",
        "settings": [
            {
                "name": "Visable in Arraylist",
                "type": 0,
                "value": 1
            }
        ],
        "visible": true
    },
    {
        "enabled": true,
        "ingameOnly": true,
        "keybind": 7,
        "name": "Interface",
        "settings": [
            {
                "name": "Visable in Arraylist",
                "type": 0,
                "value": 0
            },
            {
                "name": "Mode",
                "type": 2,
                "value": 0
            },
            {
                "name": "Color",
                "type": 2,
                "value": 0
            },
            {
                "name": "KeyStrokes",
                "type": 0,
                "value": 0
            },
            {
                "name": "Keys Scale",
                "type": 1,
                "value": 2.5
            }
        ],
        "visible": false
    },
    {
        "enabled": false,
        "ingameOnly": true,
        "keybind": 7,
        "name": "Jump Circle",
        "settings": [
            {
                "name": "Visable in Arraylist",
                "type": 0,
                "value": 1
            },
            {
                "name": "Scale",
                "type": 1,
                "value": 1.5
            },
            {
                "name": "Test",
                "type": 1,
                "value": 30.0
            },
            {
                "name": "Speed",
                "type": 1,
                "value": 1.0
            },
            {
                "name": "Fade",
                "type": 1,
                "value": 2.0
            }
        ],
        "visible": true
    },
    {
        "enabled": false,
        "ingameOnly": true,
        "keybind": 7,
        "name": "LevelInfo",
        "settings": [
            {
                "name": "Visable in Arraylist",
                "type": 0,
                "value": 1
            },
            {
                "name": "Style",
                "type": 2,
                "value": 0
            },
            {
                "name": "FPS",
                "type": 0,
                "value": 1
            },
            {
                "name": "Ping",
                "type": 0,
                "value": 1
            },
            {
                "name": "BPS",
                "type": 0,
                "value": 1
            },
            {
                "name": "XYZ",
                "type": 0,
                "value": 0
            },
            {
                "name": "SpeedSpells",
                "type": 0,
                "value": 0
            },
            {
                "name": "HealthSpells",
                "type": 0,
                "value": 0
            },
            {
                "name": "BlockInfo",
                "type": 0,
                "value": 0
            },
            {
                "name": "Pearls",
                "type": 0,
                "value": 0
            },
            {
                "name": "Arrows",
                "type": 0,
                "value": 0
            }
        ],
        "visible": true
    },
    {
        "enabled": false,
        "ingameOnly": true,
        "keybind": 7,
        "name": "NameTags",
        "settings": [
            {
                "name": "Visable in Arraylist",
                "type": 0,
                "value": 1
            },
            {
                "name": "Range",
                "type": 1,
                "value": 70.0
            },
            {
                "name": "Self",
                "type": 0,
                "value": 1
            },
            {
                "name": "Opacity",
                "type": 1,
                "value": 50.0
            },
            {
                "name": "Rounding",
                "type": 1,
                "value": 0.0
            },
            {
                "name": "Blur",
                "type": 0,
                "value": 1
            },
            {
                "name": "Ease",
                "type": 0,
                "value": 0
            },
            {
                "name": "Shadow",
                "type": 0,
                "value": 1
            },
            {
                "name": "Text Shadow",
                "type": 0,
                "value": 1
            },
            {
                "name": "Fill Shadow",
                "type": 0,
                "value": 1
            },
            {
                "name": "Shadow strenght",
                "type": 1,
                "value": 150.0
            }
        ],
        "visible": true
    },
    {
        "enabled": true,
        "ingameOnly": true,
        "keybind": 7,
        "name": "NoFire",
        "settings": [
            {
                "name": "Visable in Arraylist",
                "type": 0,
                "value": 0
            }
        ],
        "visible": false
    },
    {
        "enabled": true,
        "ingameOnly": true,
        "keybind": 7,
        "name": "Notifications",
        "settings": [
            {
                "name": "Visable in Arraylist",
                "type": 0,
                "value": 1
            }
        ],
        "visible": true
    },
    {
        "enabled": false,
        "ingameOnly": true,
        "keybind": 7,
        "name": "RedstoneESP",
        "settings": [
            {
                "name": "Visable in Arraylist",
                "type": 0,
                "value": 1
            },
            {
                "name": "Lit Redstone",
                "type": 0,
                "value": 1
            },
            {
                "name": "Range",
                "type": 1,
                "value": 20.0
            }
        ],
        "visible": true
    },
    {
        "enabled": true,
        "ingameOnly": true,
        "keybind": 7,
        "name": "ServerRotations",
        "settings": [
            {
                "name": "Visable in Arraylist",
                "type": 0,
                "value": 1
            },
            {
                "name": "LockBodyYaw",
                "type": 0,
                "value": 1
            },
            {
                "name": "Reset",
                "type": 0,
                "value": 0
            },
            {
                "name": "Yaw Speed",
                "type": 1,
                "value": 2.069999933242798
            },
            {
                "name": "Body Speed",
                "type": 1,
                "value": 1.0399999618530273
            },
            {
                "name": "Pitch Speed",
                "type": 1,
                "value": 2.069999933242798
            }
        ],
        "visible": true
    },
    {
        "enabled": false,
        "ingameOnly": true,
        "keybind": 7,
        "name": "SuperHeroFX",
        "settings": [
            {
                "name": "Visable in Arraylist",
                "type": 0,
                "value": 1
            }
        ],
        "visible": true
    },
    {
        "enabled": false,
        "ingameOnly": true,
        "keybind": 7,
        "name": "TargetHUD",
        "settings": [
            {
                "name": "Visable in Arraylist",
                "type": 0,
                "value": 1
            },
            {
                "name": "Style",
                "type": 2,
                "value": 0
            },
            {
                "name": "Track3D",
                "type": 0,
                "value": 0
            },
            {
                "name": "Track Ease",
                "type": 0,
                "value": 0
            },
            {
                "name": "Blur",
                "type": 0,
                "value": 1
            },
            {
                "name": "Rounding",
                "type": 1,
                "value": 5.0
            }
        ],
        "visible": true
    },
    {
        "enabled": false,
        "ingameOnly": true,
        "keybind": 7,
        "name": "Trail",
        "settings": [
            {
                "name": "Visable in Arraylist",
                "type": 0,
                "value": 1
            },
            {
                "name": "Time",
                "type": 1,
                "value": 1.0
            },
            {
                "name": "Delay",
                "type": 1,
                "value": 3.0
            }
        ],
        "visible": true
    },
    {
        "enabled": false,
        "ingameOnly": true,
        "keybind": 7,
        "name": "Viewmodel",
        "settings": [
            {
                "name": "Visable in Arraylist",
                "type": 0,
                "value": 1
            },
            {
                "name": "PosX",
                "type": 1,
                "value": 0.30000001192092896
            },
            {
                "name": "PosY",
                "type": 1,
                "value": -0.10000000149011612
            },
            {
                "name": "PosZ",
                "type": 1,
                "value": -1.0
            },
            {
                "name": "Rot Angle",
                "type": 1,
                "value": 0.0
            },
            {
                "name": "RotX",
                "type": 1,
                "value": 0.0
            },
            {
                "name": "RotY",
                "type": 1,
                "value": 0.0
            },
            {
                "name": "RotZ",
                "type": 1,
                "value": 0.0
            }
        ],
        "visible": true
    },
    {
        "enabled": true,
        "ingameOnly": true,
        "keybind": 7,
        "name": "Watermark",
        "settings": [
            {
                "name": "Visable in Arraylist",
                "type": 0,
                "value": 1
            },
            {
                "name": "Style",
                "type": 2,
                "value": 1
            },
            {
                "name": "Opacity",
                "type": 1,
                "value": 0.20000000298023224
            },
            {
                "name": "Shadow",
                "type": 0,
                "value": 1
            },
            {
                "name": "Fill Shadow",
                "type": 0,
                "value": 1
            },
            {
                "name": "Shadow strenght",
                "type": 1,
                "value": 150.0
            },
            {
                "name": "Radius",
                "type": 1,
                "value": 60.0
            }
        ],
        "visible": true
    }
]